atomic_red_team_mcp/__init__.py
atomic_red_team_mcp/__main__.py
atomic_red_team_mcp/models/__init__.py
atomic_red_team_mcp/models/atomic.py
atomic_red_team_mcp/server/__init__.py
atomic_red_team_mcp/server/app.py
atomic_red_team_mcp/server/auth.py
atomic_red_team_mcp/server/resources.py
atomic_red_team_mcp/services/__init__.py
atomic_red_team_mcp/services/atomic_loader.py
atomic_red_team_mcp/services/executor.py
atomic_red_team_mcp/tools/__init__.py
atomic_red_team_mcp/tools/execute_atomic.py
atomic_red_team_mcp/tools/query_atomics.py
atomic_red_team_mcp/tools/refresh_atomics.py
atomic_red_team_mcp/tools/server_info.py
atomic_red_team_mcp/tools/validate_atomic.py
atomic_red_team_mcp/utils/__init__.py
atomic_red_team_mcp/utils/config.py
atomic_red_team_mcp-1.2.6.dist-info/METADATA
atomic_red_team_mcp-1.2.6.dist-info/WHEEL
atomic_red_team_mcp-1.2.6.dist-info/entry_points.txt
atomic_red_team_mcp-1.2.6.dist-info/licenses/LICENSE
atomic_red_team_mcp-1.2.6.dist-info/RECORD
