Metadata-Version: 2.4
Name: atomic-red-team-mcp
Version: 1.2.6
Summary: MCP server providing access to Atomic Red Team security tests with search, validation, and creation capabilities
Project-URL: Homepage, https://github.com/cyberbuff/atomic-red-team-mcp
Project-URL: Documentation, https://github.com/cyberbuff/atomic-red-team-mcp
Project-URL: Repository, https://github.com/cyberbuff/atomic-red-team-mcp
Project-URL: Issues, https://github.com/cyberbuff/atomic-red-team-mcp/issues
Author: cyberbuff
License-Expression: MIT
License-File: LICENSE
Keywords: atomic-red-team,mcp
Requires-Python: >=3.10
Requires-Dist: atomic-operator>=0.8.5
Requires-Dist: fastmcp>=2.12.4
Requires-Dist: gitpython>=3.1.0
Requires-Dist: pydantic-settings>=2.0.0
Requires-Dist: pydantic>=2.0.0
Requires-Dist: pyyaml>=6.0.2
Provides-Extra: dev
Requires-Dist: bump-my-version>=0.26.1; extra == 'dev'
